axiomatic_proofkit/__init__.py
axiomatic_proofkit/build.py
axiomatic_proofkit/jcs.py
axiomatic_proofkit/publish.py
axiomatic_proofkit-0.1.3.dist-info/METADATA
axiomatic_proofkit-0.1.3.dist-info/WHEEL
axiomatic_proofkit-0.1.3.dist-info/top_level.txt
axiomatic_proofkit-0.1.3.dist-info/RECORD
