Metadata-Version: 2.4
Name: axiomatic_proofkit
Version: 0.1.3
Requires-Python: >=3.10
Requires-Dist: py-algorand-sdk<3.0,>=2.6
